blackbird/__init__.py
blackbird/_version.py
blackbird/auxiliary.py
blackbird/blackbirdLexer.py
blackbird/blackbirdListener.py
blackbird/blackbirdParser.py
blackbird/error.py
blackbird/listener.py
blackbird/program.py
blackbird/utils.py
quantum_blackbird-0.4.0.dist-info/LICENSE
quantum_blackbird-0.4.0.dist-info/METADATA
quantum_blackbird-0.4.0.dist-info/WHEEL
quantum_blackbird-0.4.0.dist-info/top_level.txt
quantum_blackbird-0.4.0.dist-info/RECORD
