Metadata-Version: 2.1
Name: quantum-blackbird
Version: 0.4.0
Summary: Blackbird is a quantum assembly language for continuous-variable quantum computation by Xanadu Inc.
Home-page: https://github.com/XanaduAI/blackbird
Maintainer: Xanadu Inc.
Maintainer-email: josh@xanadu.ai
License: Apache License 2.0
Platform: UNKNOWN
Classifier: Development Status :: 4 - Beta
Classifier: Environment :: Console
Classifier: Intended Audience :: Science/Research
Classifier: License :: OSI Approved :: Apache Software License
Classifier: Natural Language :: English
Classifier: Operating System :: POSIX
Classifier: Operating System :: MacOS :: MacOS X
Classifier: Operating System :: POSIX :: Linux
Classifier: Operating System :: Microsoft :: Windows
Classifier: Programming Language :: Python
Classifier: Programming Language :: Python :: 3
Classifier: Programming Language :: Python :: 3.6
Classifier: Programming Language :: Python :: 3.7
Classifier: Programming Language :: Python :: 3.8
Classifier: Programming Language :: Python :: 3.9
Classifier: Programming Language :: Python :: 3 :: Only
Classifier: Topic :: Scientific/Engineering :: Physics
Provides: blackbird
License-File: LICENSE
Requires-Dist: numpy (>=1.16)
Requires-Dist: sympy
Requires-Dist: antlr4-python3-runtime (==4.8)
Requires-Dist: networkx
